yamlen/__init__.py
yamlen/error.py
yamlen/loader.py
yamlen/tag/__init__.py
yamlen/tag/impl/__init__.py
yamlen/tag/impl/inclusion.py
yamlen-0.2.0.dist-info/LICENSE
yamlen-0.2.0.dist-info/WHEEL
yamlen-0.2.0.dist-info/METADATA
yamlen-0.2.0.dist-info/RECORD
