Metadata-Version: 2.1
Name: yamlen
Version: 0.2.0
Summary: A PyYAML thin wrapper.
Home-page: https://github.com/ymoch/yamlen
License: MIT
Author: Yu Mochizuki
Author-email: ymoch.dev@gmail.com
Requires-Python: >=3.7,<4.0
Classifier: Development Status :: 3 - Alpha
Classifier: Intended Audience :: Developers
Classifier: License :: OSI Approved :: MIT License
Classifier: Operating System :: OS Independent
Classifier: Programming Language :: Python :: 3
Classifier: Programming Language :: Python :: 3.10
Classifier: Programming Language :: Python :: 3.7
Classifier: Programming Language :: Python :: 3.8
Classifier: Programming Language :: Python :: 3.9
Classifier: Topic :: Software Development :: Libraries :: Python Modules
Classifier: Topic :: Text Processing :: Markup
Requires-Dist: pyyaml (>=6.0,<7.0)
Project-URL: Repository, https://github.com/ymoch/yamlen
